LICENSE
MANIFEST.in
setup.py
djangocms_toc/__init__.py
djangocms_toc/cms_plugins.py
djangocms_toc/models.py
djangocms_toc.egg-info/PKG-INFO
djangocms_toc.egg-info/SOURCES.txt
djangocms_toc.egg-info/dependency_links.txt
djangocms_toc.egg-info/top_level.txt
djangocms_toc/migrations/0001_initial.py
djangocms_toc/migrations/__init__.py
djangocms_toc/templates/cms/plugins/toc.html
djangocms_toc/templates/cms/plugins/toc_branch.html
djangocms_toc/templatetags/__init__.py
djangocms_toc/templatetags/cms_toc.py