Metadata-Version: 1.0
Name: djangocms-toc
Version: 1.0.1
Summary: Table of Contents Plugin for django CMS
Home-page: None
Author: Martin Owens
Author-email: doctormo@gmail.com
License: AGPLv3
Platform: UNKNOWN
